Metadata-Version: 1.0
Name: pynotifyx
Version: 0.3.7
Summary: pynotifyx is a simple Python binding to the Linux inotify file system event monitoring API.
Home-page: https://github.com/joeisca/pynotifyx/
Author: Joe Isca
Author-email: joeisca@gmail.com
License: UNKNOWN
Platform: UNKNOWN
